opentracing_instrumentation/__init__.py
opentracing_instrumentation/config.py
opentracing_instrumentation/http_client.py
opentracing_instrumentation/http_server.py
opentracing_instrumentation/interceptors.py
opentracing_instrumentation/local_span.py
opentracing_instrumentation/request_context.py
opentracing_instrumentation/utils.py
opentracing_instrumentation/client_hooks/__init__.py
opentracing_instrumentation/client_hooks/_current_span.py
opentracing_instrumentation/client_hooks/_dbapi2.py
opentracing_instrumentation/client_hooks/_patcher.py
opentracing_instrumentation/client_hooks/_singleton.py
opentracing_instrumentation/client_hooks/boto3.py
opentracing_instrumentation/client_hooks/celery.py
opentracing_instrumentation/client_hooks/mysqldb.py
opentracing_instrumentation/client_hooks/psycopg2.py
opentracing_instrumentation/client_hooks/requests.py
opentracing_instrumentation/client_hooks/sqlalchemy.py
opentracing_instrumentation/client_hooks/strict_redis.py
opentracing_instrumentation/client_hooks/tornado_http.py
opentracing_instrumentation/client_hooks/urllib.py
opentracing_instrumentation/client_hooks/urllib2.py
opentracing_instrumentation-3.2.1.dist-info/LICENSE
opentracing_instrumentation-3.2.1.dist-info/METADATA
opentracing_instrumentation-3.2.1.dist-info/WHEEL
opentracing_instrumentation-3.2.1.dist-info/top_level.txt
opentracing_instrumentation-3.2.1.dist-info/RECORD
