Metadata-Version: 2.1
Name: opentracing-instrumentation
Version: 3.2.1
Summary: Tracing Instrumentation using OpenTracing API (http://opentracing.io)
Home-page: https://github.com/uber-common/opentracing-python-instrumentation
Author: Yuri Shkuro
Author-email: ys@uber.com
License: MIT
Keywords: opentracing
Platform: any
Classifier: Development Status :: 5 - Production/Stable
Classifier: Intended Audience :: Developers
Classifier: License :: OSI Approved :: MIT License
Classifier: Programming Language :: Python :: 2.7
Classifier: Programming Language :: Python :: 3.5
Classifier: Programming Language :: Python :: 3.6
Classifier: Programming Language :: Python :: 3.7
Classifier: Programming Language :: Python :: Implementation :: PyPy
Classifier: Topic :: Software Development :: Libraries :: Python Modules
Requires-Dist: future
Requires-Dist: wrapt
Requires-Dist: tornado (<6,>=4.1)
Requires-Dist: contextlib2
Requires-Dist: opentracing (<3,>=2)
Requires-Dist: six
Provides-Extra: tests
Requires-Dist: boto3 ; extra == 'tests'
Requires-Dist: botocore ; extra == 'tests'
Requires-Dist: celery ; extra == 'tests'
Requires-Dist: doubles ; extra == 'tests'
Requires-Dist: flake8 ; extra == 'tests'
Requires-Dist: flake8-quotes ; extra == 'tests'
Requires-Dist: mock ; extra == 'tests'
Requires-Dist: moto ; extra == 'tests'
Requires-Dist: psycopg2-binary ; extra == 'tests'
Requires-Dist: sqlalchemy (>=1.3.7) ; extra == 'tests'
Requires-Dist: pytest ; extra == 'tests'
Requires-Dist: pytest-cov ; extra == 'tests'
Requires-Dist: pytest-localserver ; extra == 'tests'
Requires-Dist: pytest-mock ; extra == 'tests'
Requires-Dist: pytest-tornado ; extra == 'tests'
Requires-Dist: basictracer (<4,>=3) ; extra == 'tests'
Requires-Dist: redis ; extra == 'tests'
Requires-Dist: Sphinx ; extra == 'tests'
Requires-Dist: sphinx-rtd-theme ; extra == 'tests'
Requires-Dist: testfixtures ; extra == 'tests'
Requires-Dist: MySQL-python ; (python_version == "2.7") and extra == 'tests'
